{
    "allowedTokens": [
        {
            "phone": "A",
            "token_id": "aaaaaa"
        },
        {
            "phone": "Uuuu",
            "token_id": "aaaaa"
        },
        {
            "phone": "UuuuKhun",
            "token_id": "234567"
        },
        {
            "phone": "Yyyuhhgh",
            "token_id": "345677"
        },
        {
            "phone": "zdyuh",
            "token_id": "566789"
        },
        {
            "phone": "tttyKr",
            "token_id": "223567"
        }
    ]
}